ats_sdk/__init__.py
ats_sdk/domain.py
ats_sdk/error.py
ats_sdk/services.py
ats_sdk/translation.py
tests/__init__.py
tests/test_services.py
tests/test_translation.py
ats_sdk-0.0.7.dist-info/METADATA
ats_sdk-0.0.7.dist-info/WHEEL
ats_sdk-0.0.7.dist-info/top_level.txt
ats_sdk-0.0.7.dist-info/RECORD
